README.rst
setup.py
libpebble2/__init__.py
libpebble2/exceptions.py
libpebble2/version.py
libpebble2.egg-info/PKG-INFO
libpebble2.egg-info/SOURCES.txt
libpebble2.egg-info/dependency_links.txt
libpebble2.egg-info/requires.txt
libpebble2.egg-info/top_level.txt
libpebble2.egg-info/zip-safe
libpebble2/communication/__init__.py
libpebble2/communication/transports/__init__.py
libpebble2/communication/transports/pulse.py
libpebble2/communication/transports/serial.py
libpebble2/communication/transports/qemu/__init__.py
libpebble2/communication/transports/qemu/protocol.py
libpebble2/communication/transports/websocket/__init__.py
libpebble2/communication/transports/websocket/protocol.py
libpebble2/events/__init__.py
libpebble2/events/mixin.py
libpebble2/events/threaded.py
libpebble2/protocol/__init__.py
libpebble2/protocol/appglance.py
libpebble2/protocol/appmessage.py
libpebble2/protocol/apps.py
libpebble2/protocol/audio.py
libpebble2/protocol/blobdb.py
libpebble2/protocol/data_logging.py
libpebble2/protocol/legacy2.py
libpebble2/protocol/logs.py
libpebble2/protocol/meta.py
libpebble2/protocol/music.py
libpebble2/protocol/phone.py
libpebble2/protocol/screenshots.py
libpebble2/protocol/system.py
libpebble2/protocol/timeline.py
libpebble2/protocol/transfers.py
libpebble2/protocol/voice.py
libpebble2/protocol/base/__init__.py
libpebble2/protocol/base/types.py
libpebble2/services/__init__.py
libpebble2/services/appglances.py
libpebble2/services/appmessage.py
libpebble2/services/blobdb.py
libpebble2/services/data_logging.py
libpebble2/services/getbytes.py
libpebble2/services/install.py
libpebble2/services/notifications.py
libpebble2/services/putbytes.py
libpebble2/services/screenshot.py
libpebble2/services/voice.py
libpebble2/util/__init__.py
libpebble2/util/bundle.py
libpebble2/util/hardware.py
libpebble2/util/stm32_crc.py