Metadata-Version: 1.1
Name: libpebble2
Version: 0.0.25
Summary: Library for communicating with pebbles over pebble protocol
Home-page: https://github.com/pebble/libpebble2
Author: Pebble Technology Corporation
Author-email: katharine@pebble.com
License: MIT
Platform: UNKNOWN
Classifier: Development Status :: 3 - Alpha
Classifier: Intended Audience :: Developers
Classifier: License :: OSI Approved :: MIT License
Classifier: Operating System :: MacOS :: MacOS X
Classifier: Operating System :: POSIX
Classifier: Programming Language :: Python :: 2
Classifier: Programming Language :: Python :: 2.7
Classifier: Programming Language :: Python :: 3
Classifier: Programming Language :: Python :: 3.4
Classifier: Topic :: Software Development :: Libraries :: Python Modules
Classifier: Topic :: Software Development :: Embedded Systems
